snc4onnx/__init__.py
snc4onnx/__main__.py
snc4onnx/onnx_network_combine.py
snc4onnx-1.0.14.dist-info/licenses/LICENSE
snc4onnx-1.0.14.dist-info/METADATA
snc4onnx-1.0.14.dist-info/WHEEL
snc4onnx-1.0.14.dist-info/entry_points.txt
snc4onnx-1.0.14.dist-info/top_level.txt
snc4onnx-1.0.14.dist-info/RECORD
