Metadata-Version: 2.4
Name: snc4onnx
Version: 1.0.14
Summary: Simple tool to combine onnx models. Simple Network Combine Tool for ONNX.
Home-page: https://github.com/PINTO0309/sne4onnx
Author: Katsuya Hyodo
Author-email: rmsdh122@yahoo.co.jp
License: MIT License
Platform: linux
Platform: unix
Requires-Python: >=3.6
License-File: LICENSE
Dynamic: author
Dynamic: author-email
Dynamic: description
Dynamic: description-content-type
Dynamic: home-page
Dynamic: license
Dynamic: license-file
Dynamic: platform
Dynamic: requires-python
Dynamic: summary
